phantasy_rest/__init__.py
phantasy_rest/_cache.py
phantasy_rest/_gconf.py
phantasy_rest/_get_conf.py
phantasy_rest/config.toml
phantasy_rest/dependencies.py
phantasy_rest/main.py
phantasy_rest/db/__init__.py
phantasy_rest/db/dals/__init__.py
phantasy_rest/db/dals/device_dal.py
phantasy_rest/db/models/__init__.py
phantasy_rest/db/models/device.py
phantasy_rest/routers/__init__.py
phantasy_rest/routers/ca_router.py
phantasy_rest/routers/misc_router.py
phantasy_rest/routers/mp_router.py
phantasy_rest/routers/phy_router.py
phantasy_rest/static/buttons.dataTables.min.css
phantasy_rest/static/buttons.html5.min.js
phantasy_rest/static/chart.umd.min.js
phantasy_rest/static/chartjs-plugin-zoom.min.js
phantasy_rest/static/dataTables.buttons.min.js
phantasy_rest/static/dataTables.scroller.min.js
phantasy_rest/static/dataTables.select.min.js
phantasy_rest/static/jquery-3.5.1.min.js
phantasy_rest/static/jquery.dataTables.min.css
phantasy_rest/static/jquery.dataTables.min.js
phantasy_rest/static/scroller.dataTables.min.css
phantasy_rest/static/select.dataTables.min.css
phantasy_rest/static/style.css
phantasy_rest/static/bootstrap5/bootstrap.min.css
phantasy_rest/static/bootstrap5/bootstrap.min.js
phantasy_rest/templates/table.html
phantasy_rest-0.6.7.dist-info/LICENSE
phantasy_rest-0.6.7.dist-info/METADATA
phantasy_rest-0.6.7.dist-info/WHEEL
phantasy_rest-0.6.7.dist-info/entry_points.txt
phantasy_rest-0.6.7.dist-info/top_level.txt
phantasy_rest-0.6.7.dist-info/RECORD
